<?xml version="1.0" encoding="UTF-8"?>
<databaseChangeLog
        xmlns="http://www.liquibase.org/xml/ns/dbchangelog"
        xmlns:xsi="http://www.w3.org/2001/XMLSchema-instance"
        xmlns:ext="http://www.liquibase.org/xml/ns/dbchangelog-ext"
        xmlns:pro="http://www.liquibase.org/xml/ns/pro"
        xsi:schemaLocation="http://www.liquibase.org/xml/ns/dbchangelog
        http://www.liquibase.org/xml/ns/dbchangelog/dbchangelog-latest.xsd
        http://www.liquibase.org/xml/ns/dbchangelog-ext
        http://www.liquibase.org/xml/ns/dbchangelog/dbchangelog-ext.xsd
        http://www.liquibase.org/xml/ns/pro
        http://www.liquibase.org/xml/ns/pro/liquibase-pro-latest.xsd"
        objectQuotingStrategy="QUOTE_ONLY_RESERVED_WORDS"
>
    <changeSet id="21" author="Eversis">
        <comment>Saved searches</comment>
        <addColumn tableName="saved_searches">
            <column name="name" type="varchar(254)">
                <constraints nullable="false"/>
            </column>
        </addColumn>
        <addColumn tableName="saved_searches_aud">
            <column name="name" type="varchar(254)">
            </column>
        </addColumn>
    </changeSet>
</databaseChangeLog>
